django_site_fer/__init__.py
django_site_fer/admin.py
django_site_fer/apps.py
django_site_fer/cli.py
django_site_fer/generate.py
django_site_fer/models.py
django_site_fer/tests.py
django_site_fer/urls.py
django_site_fer/views.py
django_site_fer/migrations/__init__.py
django_site_fer/static/script.js
django_site_fer/static/style.css
django_site_fer/templates/base.html
django_site_fer-0.3.1.dist-info/licenses/LICENSE
django_site_fer-0.3.1.dist-info/METADATA
django_site_fer-0.3.1.dist-info/WHEEL
django_site_fer-0.3.1.dist-info/entry_points.txt
django_site_fer-0.3.1.dist-info/top_level.txt
django_site_fer-0.3.1.dist-info/RECORD
